Exchange/__init__.py
Exchange/huobiexchange.py
Exchangesetting/__init__.py
Exchangesetting/dcpsetting.py
Exchangesetting/gpvarsetting.py
Exchangesetting/urlinfosetting.py
Exchangetools/__init__.py
Exchangetools/dctools.py
dclibzh-0.0.1.dist-info/LICENSE
dclibzh-0.0.1.dist-info/METADATA
dclibzh-0.0.1.dist-info/WHEEL
dclibzh-0.0.1.dist-info/top_level.txt
dclibzh-0.0.1.dist-info/RECORD
