Metadata-Version: 2.1
Name: dclibzh
Version: 0.0.1
Summary: 数字火币交易平台
Home-page: https://gitee.com/dadafrancis/dclibzh
Author: Francis
Author-email: jundayan39@Gmail.com
License: UNKNOWN
Platform: UNKNOWN
Classifier: Programming Language :: Python :: 3
Classifier: License :: OSI Approved :: MIT License
Classifier: Operating System :: OS Independent
